tdl_nest/__init__.py
tdl_nest/nest.py
tdl_nest-0.1.0.dist-info/LICENSE
tdl_nest-0.1.0.dist-info/METADATA
tdl_nest-0.1.0.dist-info/WHEEL
tdl_nest-0.1.0.dist-info/RECORD
