Metadata-Version: 2.1
Name: tdl-nest
Version: 0.1.0
Summary: simple library to iterate through nested dict, list, and tuples
Author: Daniel L Marino
Author-email: daniellml55@gmail.com
Requires-Python: >=3.10,<4.0
Classifier: Programming Language :: Python :: 3
Classifier: Programming Language :: Python :: 3.10
Classifier: Programming Language :: Python :: 3.11
Classifier: Programming Language :: Python :: 3.12
